{
  "project_info": {
    "project_number": "495035301106",
    "project_id": "fala-doutor-challenge",
    "storage_bucket": "fala-doutor-challenge.firebasestorage.app"
  },
  "client": [
    {
      "client_info": {
        "mobilesdk_app_id": "1:495035301106:android:0451bcd8ea28c9e940a46b",
        "android_client_info": {
          "package_name": "com.example.fala_doutor_challenge"
        }
      },
      "oauth_client": [],
      "api_key": [
        {
          "current_key": "AIzaSyDdiOEYwchQDJhRjTG5myIOAiOEV-o4COQ"
        }
      ],
      "services": {
        "appinvite_service": {
          "other_platform_oauth_client": []
        }
      }
    }
  ],
  "configuration_version": "1"
}